<?xml version="1.0" encoding="UTF-8" standalone="no"?>
<file>
<func>
<list>
<leaf symbol="DEF" />
<list>
<leaf symbol="ComplexRootFindingPackage" />
<leaf symbol="R" />
<leaf symbol="UP" />
</list>
<list>
<list>
<leaf symbol="CATEGORY" />
<leaf symbol="package" />
<list>
<leaf symbol="SIGNATURE" />
<leaf symbol="complexZeros" />
<list>
<list>
<leaf symbol="List" />
<list>
<leaf symbol="Complex" />
<leaf symbol="R" />
</list>
</list>
<leaf symbol="UP" />
</list>
</list>
<list>
<leaf symbol="SIGNATURE" />
<leaf symbol="complexZeros" />
<list>
<list>
<leaf symbol="List" />
<list>
<leaf symbol="Complex" />
<leaf symbol="R" />
</list>
</list>
<leaf symbol="UP" />
<leaf symbol="R" />
</list>
</list>
<list>
<leaf symbol="SIGNATURE" />
<leaf symbol="divisorCascade" />
<list>
<list>
<leaf symbol="List" />
<list>
<leaf symbol="Record" />
<list>
<leaf symbol=":" />
<leaf symbol="factors" />
<list>
<leaf symbol="List" />
<leaf symbol="UP" />
</list>
</list>
<list>
<leaf symbol=":" />
<leaf symbol="error" />
<leaf symbol="R" />
</list>
</list>
</list>
<leaf symbol="UP" />
<leaf symbol="UP" />
<list>
<leaf symbol="Boolean" />
</list>
</list>
</list>
<list>
<leaf symbol="SIGNATURE" />
<leaf symbol="divisorCascade" />
<list>
<list>
<leaf symbol="List" />
<list>
<leaf symbol="Record" />
<list>
<leaf symbol=":" />
<leaf symbol="factors" />
<list>
<leaf symbol="List" />
<leaf symbol="UP" />
</list>
</list>
<list>
<leaf symbol=":" />
<leaf symbol="error" />
<leaf symbol="R" />
</list>
</list>
</list>
<leaf symbol="UP" />
<leaf symbol="UP" />
</list>
</list>
<list>
<leaf symbol="SIGNATURE" />
<leaf symbol="factor" />
<list>
<list>
<leaf symbol="Factored" />
<leaf symbol="UP" />
</list>
<leaf symbol="UP" />
<leaf symbol="R" />
<list>
<leaf symbol="Boolean" />
</list>
</list>
</list>
<list>
<leaf symbol="SIGNATURE" />
<leaf symbol="factor" />
<list>
<list>
<leaf symbol="Factored" />
<leaf symbol="UP" />
</list>
<leaf symbol="UP" />
<leaf symbol="R" />
</list>
</list>
<list>
<leaf symbol="SIGNATURE" />
<leaf symbol="factor" />
<list>
<list>
<leaf symbol="Factored" />
<leaf symbol="UP" />
</list>
<leaf symbol="UP" />
</list>
</list>
<list>
<leaf symbol="SIGNATURE" />
<leaf symbol="graeffe" />
<list>
<leaf symbol="UP" />
<leaf symbol="UP" />
</list>
</list>
<list>
<leaf symbol="SIGNATURE" />
<leaf symbol="norm" />
<list>
<leaf symbol="R" />
<leaf symbol="UP" />
</list>
</list>
<list>
<leaf symbol="SIGNATURE" />
<leaf symbol="pleskenSplit" />
<list>
<list>
<leaf symbol="Factored" />
<leaf symbol="UP" />
</list>
<leaf symbol="UP" />
<leaf symbol="R" />
<list>
<leaf symbol="Boolean" />
</list>
</list>
</list>
<list>
<leaf symbol="SIGNATURE" />
<leaf symbol="pleskenSplit" />
<list>
<list>
<leaf symbol="Factored" />
<leaf symbol="UP" />
</list>
<leaf symbol="UP" />
<leaf symbol="R" />
</list>
</list>
<list>
<leaf symbol="SIGNATURE" />
<leaf symbol="reciprocalPolynomial" />
<list>
<leaf symbol="UP" />
<leaf symbol="UP" />
</list>
</list>
<list>
<leaf symbol="SIGNATURE" />
<leaf symbol="rootRadius" />
<list>
<leaf symbol="R" />
<leaf symbol="UP" />
<leaf symbol="R" />
</list>
</list>
<list>
<leaf symbol="SIGNATURE" />
<leaf symbol="rootRadius" />
<list>
<leaf symbol="R" />
<leaf symbol="UP" />
</list>
</list>
<list>
<leaf symbol="SIGNATURE" />
<leaf symbol="schwerpunkt" />
<list>
<list>
<leaf symbol="Complex" />
<leaf symbol="R" />
</list>
<leaf symbol="UP" />
</list>
</list>
<list>
<leaf symbol="SIGNATURE" />
<leaf symbol="setErrorBound" />
<list>
<leaf symbol="R" />
<leaf symbol="R" />
</list>
</list>
<list>
<leaf symbol="SIGNATURE" />
<leaf symbol="startPolynomial" />
<list>
<list>
<leaf symbol="Record" />
<list>
<leaf symbol=":" />
<leaf symbol="start" />
<leaf symbol="UP" />
</list>
<list>
<leaf symbol=":" />
<leaf symbol="factors" />
<list>
<leaf symbol="Factored" />
<leaf symbol="UP" />
</list>
</list>
</list>
<leaf symbol="UP" />
</list>
</list>
</list>
<list>
<leaf symbol="Join" />
<list>
<leaf symbol="Field" />
</list>
<list>
<leaf symbol="OrderedRing" />
</list>
</list>
<list>
<leaf symbol="UnivariatePolynomialCategory" />
<list>
<leaf symbol="Complex" />
<leaf symbol="R" />
</list>
</list>
</list>
<list>
<list />
<list />
<list />
</list>
<list>
<leaf symbol="CAPSULE" />
<list>
<leaf symbol="LET" />
<leaf symbol="Rep" />
<list>
<leaf symbol="ModMonic" />
<list>
<leaf symbol="Complex" />
<leaf symbol="R" />
</list>
<leaf symbol="UP" />
</list>
</list>
<list>
<leaf symbol=":" />
<leaf symbol="c" />
<list>
<leaf symbol="Complex" />
<leaf symbol="R" />
</list>
</list>
<list>
<leaf symbol=":" />
<leaf symbol="r" />
<leaf symbol="R" />
</list>
<list>
<leaf symbol="LET" />
<list>
<leaf symbol=":" />
<leaf symbol="globalDigits" />
<list>
<leaf symbol="Integer" />
</list>
</list>
<list>
<leaf symbol="^" />
<leaf int="10" />
<leaf int="7" />
</list>
</list>
<list>
<leaf symbol="LET" />
<list>
<leaf symbol=":" />
<leaf symbol="globalEps" />
<leaf symbol="R" />
</list>
<list>
<leaf symbol="SEQ" />
<list>
<leaf symbol="LET" />
<list>
<leaf symbol=":" />
<leaf symbol="a" />
<leaf symbol="R" />
</list>
<list>
<leaf symbol="::" />
<list>
<leaf symbol="::" />
<leaf int="1000" />
<list>
<leaf symbol="Integer" />
</list>
</list>
<leaf symbol="R" />
</list>
</list>
<list>
<leaf symbol="exit" />
<leaf int="1" />
<list>
<leaf symbol="/" />
<list>
<leaf symbol="One" />
</list>
<leaf symbol="a" />
</list>
</list>
</list>
</list>
<list>
<leaf symbol="LET" />
<list>
<leaf symbol=":" />
<leaf symbol="emptyLine" />
<list>
<leaf symbol="OutputForm" />
</list>
</list>
<list>
<leaf symbol="message" />
<leaf string="  " />
</list>
</list>
<list>
<leaf symbol="LET" />
<list>
<leaf symbol=":" />
<leaf symbol="dashes" />
<list>
<leaf symbol="OutputForm" />
</list>
</list>
<list>
<leaf symbol="center" />
<list>
<leaf symbol="message" />
<leaf string="---------------------------------------------------" />
</list>
</list>
</list>
<list>
<leaf symbol="LET" />
<list>
<leaf symbol=":" />
<leaf symbol="dots" />
<list>
<leaf symbol="OutputForm" />
</list>
</list>
<list>
<leaf symbol="center" />
<list>
<leaf symbol="message" />
<leaf string="..................................................." />
</list>
</list>
</list>
<list>
<leaf symbol="LET" />
<list>
<leaf symbol=":" />
<leaf symbol="one" />
<leaf symbol="R" />
</list>
<list>
<leaf symbol="Sel" />
<leaf symbol="R" />
<list>
<leaf symbol="One" />
</list>
</list>
</list>
<list>
<leaf symbol="LET" />
<list>
<leaf symbol=":" />
<leaf symbol="two" />
<leaf symbol="R" />
</list>
<list>
<leaf symbol="*" />
<leaf int="2" />
<leaf symbol="one" />
</list>
</list>
<list>
<leaf symbol="LET" />
<list>
<leaf symbol=":" />
<leaf symbol="ten" />
<leaf symbol="R" />
</list>
<list>
<leaf symbol="*" />
<leaf int="10" />
<leaf symbol="one" />
</list>
</list>
<list>
<leaf symbol="LET" />
<list>
<leaf symbol=":" />
<leaf symbol="eleven" />
<leaf symbol="R" />
</list>
<list>
<leaf symbol="*" />
<leaf int="11" />
<leaf symbol="one" />
</list>
</list>
<list>
<leaf symbol="LET" />
<leaf symbol="weakEps" />
<list>
<leaf symbol="/" />
<leaf symbol="eleven" />
<leaf symbol="ten" />
</list>
</list>
<list>
<leaf symbol=":" />
<leaf symbol="absC" />
<list>
<leaf symbol="Mapping" />
<leaf symbol="R" />
<list>
<leaf symbol="Complex" />
<leaf symbol="R" />
</list>
</list>
</list>
<list>
<leaf symbol=":" />
<leaf symbol="absR" />
<list>
<leaf symbol="Mapping" />
<leaf symbol="R" />
<leaf symbol="R" />
</list>
</list>
<list>
<leaf symbol=":" />
<leaf symbol="calculateScale" />
<list>
<leaf symbol="Mapping" />
<leaf symbol="R" />
<leaf symbol="UP" />
</list>
</list>
<list>
<leaf symbol=":" />
<leaf symbol="makeMonic" />
<list>
<leaf symbol="Mapping" />
<leaf symbol="UP" />
<leaf symbol="UP" />
</list>
</list>
<list>
<leaf symbol=":" />
<leaf symbol="min" />
<list>
<leaf symbol="Mapping" />
<list>
<leaf symbol="Record" />
<list>
<leaf symbol=":" />
<leaf symbol="factors" />
<list>
<leaf symbol="List" />
<leaf symbol="UP" />
</list>
</list>
<list>
<leaf symbol=":" />
<leaf symbol="error" />
<leaf symbol="R" />
</list>
</list>
<list>
<leaf symbol="Record" />
<list>
<leaf symbol=":" />
<leaf symbol="factors" />
<list>
<leaf symbol="List" />
<leaf symbol="UP" />
</list>
</list>
<list>
<leaf symbol=":" />
<leaf symbol="error" />
<leaf symbol="R" />
</list>
</list>
<list>
<leaf symbol="Record" />
<list>
<leaf symbol=":" />
<leaf symbol="factors" />
<list>
<leaf symbol="List" />
<leaf symbol="UP" />
</list>
</list>
<list>
<leaf symbol=":" />
<leaf symbol="error" />
<leaf symbol="R" />
</list>
</list>
</list>
</list>
<list>
<leaf symbol=":" />
<leaf symbol="nthRoot" />
<list>
<leaf symbol="Mapping" />
<leaf symbol="R" />
<leaf symbol="R" />
<list>
<leaf symbol="NonNegativeInteger" />
</list>
</list>
</list>
<list>
<leaf symbol=":" />
<leaf symbol="shift" />
<list>
<leaf symbol="Mapping" />
<leaf symbol="UP" />
<leaf symbol="UP" />
<list>
<leaf symbol="Complex" />
<leaf symbol="R" />
</list>
</list>
</list>
<list>
<leaf symbol=":" />
<leaf symbol="scale" />
<list>
<leaf symbol="Mapping" />
<leaf symbol="UP" />
<leaf symbol="UP" />
<list>
<leaf symbol="Complex" />
<leaf symbol="R" />
</list>
</list>
</list>
<list>
<leaf symbol="DEF" />
<list>
<leaf symbol="complexZeros" />
<leaf symbol="p" />
<leaf symbol="eps" />
</list>
<list>
<list />
<list />
<list />
</list>
<list>
<list />
<list />
<list />
</list>
<list>
<leaf symbol="SEQ" />
<list>
<leaf symbol="LET" />
<list>
<leaf symbol=":" />
<leaf symbol="eps0" />
<leaf symbol="R" />
</list>
<list>
<leaf symbol="/" />
<leaf symbol="eps" />
<list>
<leaf symbol="^" />
<leaf symbol="ten" />
<list>
<leaf symbol="degree" />
<leaf symbol="p" />
</list>
</list>
</list>
</list>
<list>
<leaf symbol="LET" />
<list>
<leaf symbol=":" />
<leaf symbol="facs" />
<list>
<leaf symbol="Factored" />
<leaf symbol="UP" />
</list>
</list>
<list>
<leaf symbol="factor" />
<leaf symbol="p" />
<leaf symbol="eps0" />
</list>
</list>
<list>
<leaf symbol="exit" />
<leaf int="1" />
<list>
<leaf symbol="COLLECT" />
<list>
<leaf symbol="IN" />
<leaf symbol="linfac" />
<list>
<leaf symbol="factors" />
<leaf symbol="facs" />
</list>
</list>
<list>
<leaf symbol="-" />
<list>
<leaf symbol="coefficient" />
<list>
<leaf symbol="linfac" />
<leaf symbol="factor" />
</list>
<list>
<leaf symbol="Zero" />
</list>
</list>
</list>
</list>
</list>
</list>
</list>
<list>
<leaf symbol="DEF" />
<list>
<leaf symbol="complexZeros" />
<leaf symbol="p" />
</list>
<list>
<list />
<list />
</list>
<list>
<list />
<list />
</list>
<list>
<leaf symbol="complexZeros" />
<leaf symbol="p" />
<leaf symbol="globalEps" />
</list>
</list>
<list>
<leaf symbol="DEF" />
<list>
<leaf symbol="setErrorBound" />
<leaf symbol="r" />
</list>
<list>
<list />
<list />
</list>
<list>
<list />
<list />
</list>
<list>
<leaf symbol="IF" />
<list>
<leaf symbol="&lt;=" />
<leaf symbol="r" />
<list>
<leaf symbol="Zero" />
</list>
</list>
<list>
<leaf symbol="error" />
<leaf string="setErrorBound: need error bound greater 0" />
</list>
<list>
<leaf symbol="SEQ" />
<list>
<leaf symbol="LET" />
<leaf symbol="globalEps" />
<leaf symbol="r" />
</list>
<list>
<leaf symbol="IF" />
<list>
<leaf symbol="has" />
<leaf symbol="R" />
<list>
<leaf symbol="QuotientFieldCategory" />
<list>
<leaf symbol="Integer" />
</list>
</list>
</list>
<list>
<leaf symbol="SEQ" />
<list>
<leaf symbol="LET" />
<list>
<leaf symbol=":" />
<leaf symbol="rd" />
<list>
<leaf symbol="Integer" />
</list>
</list>
<list>
<leaf symbol="ceiling" />
<list>
<leaf symbol="/" />
<list>
<leaf symbol="One" />
</list>
<leaf symbol="r" />
</list>
</list>
</list>
<list>
<leaf symbol="LET" />
<leaf symbol="globalDigits" />
<list>
<leaf symbol="*" />
<list>
<leaf symbol="*" />
<leaf symbol="rd" />
<leaf symbol="rd" />
</list>
<leaf int="10" />
</list>
</list>
<list>
<leaf symbol="LET" />
<list>
<leaf symbol=":" />
<leaf symbol="lof" />
<list>
<leaf symbol="List" />
<list>
<leaf symbol="OutputForm" />
</list>
</list>
</list>
<list>
<leaf symbol="construct" />
<list>
<leaf symbol="message" />
<leaf string="setErrorBound: internal digits set to" />
</list>
<list>
<leaf symbol="::" />
<leaf symbol="globalDigits" />
<list>
<leaf symbol="OutputForm" />
</list>
</list>
</list>
</list>
<list>
<leaf symbol="exit" />
<leaf int="1" />
<list>
<leaf symbol="print" />
<list>
<leaf symbol="hconcat" />
<leaf symbol="lof" />
</list>
</list>
</list>
</list>
<leaf symbol="noBranch" />
</list>
<list>
<leaf symbol="messagePrint" />
<leaf string="setErrorBound: internal error bound set to" />
</list>
<list>
<leaf symbol="exit" />
<leaf int="1" />
<leaf symbol="globalEps" />
</list>
</list>
</list>
</list>
<list>
<leaf symbol="DEF" />
<list>
<leaf symbol="pleskenSplit" />
<leaf symbol="poly" />
<leaf symbol="eps" />
<leaf symbol="info" />
</list>
<list>
<list />
<list />
<list />
<list />
</list>
<list>
<list />
<list />
<list />
<list />
</list>
<list>
<leaf symbol="SEQ" />
<list>
<leaf symbol="LET" />
<leaf symbol="p" />
<list>
<leaf symbol="makeMonic" />
<leaf symbol="poly" />
</list>
</list>
<list>
<leaf symbol=":" />
<leaf symbol="fp" />
<list>
<leaf symbol="Factored" />
<leaf symbol="UP" />
</list>
</list>
<list>
<leaf symbol="SEQ" />
<list>
<leaf symbol="LET" />
<list>
<leaf symbol=":" />
<leaf symbol="G15840039" />
<list>
<leaf symbol="Boolean" />
</list>
</list>
<list>
<leaf symbol="zero?" />
<list>
<leaf symbol="LET" />
<leaf symbol="md" />
<list>
<leaf symbol="minimumDegree" />
<leaf symbol="p" />
</list>
</list>
</list>
</list>
<list>
<leaf symbol="exit" />
<leaf int="1" />
<list>
<leaf symbol="IF" />
<leaf symbol="G15840039" />
<leaf symbol="noBranch" />
<list>
<leaf symbol="SEQ" />
<list>
<leaf symbol="LET" />
<list>
<leaf symbol=":" />
<leaf symbol="fp" />
<list>
<leaf symbol="Factored" />
<leaf symbol="UP" />
</list>
</list>
<list>
<list>
<leaf symbol="Sel" />
<list>
<leaf symbol="Factored" />
<leaf symbol="UP" />
</list>
<leaf symbol="irreducibleFactor" />
</list>
<list>
<list>
<leaf symbol="Sel" />
<leaf symbol="UP" />
<leaf symbol="monomial" />
</list>
<list>
<leaf symbol="One" />
</list>
<list>
<leaf symbol="One" />
</list>
</list>
<leaf symbol="md" />
</list>
</list>
<list>
<leaf symbol="exit" />
<leaf int="1" />
<list>
<leaf symbol="LET" />
<leaf symbol="p" />
<list>
<leaf symbol="quo" />
<leaf symbol="p" />
<list>
<list>
<leaf symbol="Sel" />
<leaf symbol="UP" />
<leaf symbol="monomial" />
</list>
<list>
<leaf symbol="One" />
</list>
<leaf symbol="md" />
</list>
</list>
</list>
</list>
</list>
</list>
</list>
</list>
<list>
<leaf symbol="LET" />
<list>
<leaf symbol=":" />
<leaf symbol="sP" />
<list>
<leaf symbol="Record" />
<list>
<leaf symbol=":" />
<leaf symbol="start" />
<leaf symbol="UP" />
</list>
<list>
<leaf symbol=":" />
<leaf symbol="factors" />
<list>
<leaf symbol="Factored" />
<leaf symbol="UP" />
</list>
</list>
</list>
</list>
<list>
<leaf symbol="startPolynomial" />
<leaf symbol="p" />
</list>
</list>
<list>
<leaf symbol="LET" />
<list>
<leaf symbol=":" />
<leaf symbol="fp" />
<list>
<leaf symbol="Factored" />
<leaf symbol="UP" />
</list>
</list>
<list>
<leaf symbol="sP" />
<leaf symbol="factors" />
</list>
</list>
<list>
<leaf symbol="IF" />
<list>
<leaf symbol="=" />
<leaf symbol="fp" />
<list>
<leaf symbol="One" />
</list>
</list>
<leaf symbol="noBranch" />
<list>
<leaf symbol="SEQ" />
<list>
<leaf symbol="LET" />
<list>
<leaf symbol=":" />
<leaf symbol="qr" />
<list>
<leaf symbol="Record" />
<list>
<leaf symbol=":" />
<leaf symbol="quotient" />
<leaf symbol="UP" />
</list>
<list>
<leaf symbol=":" />
<leaf symbol="remainder" />
<leaf symbol="UP" />
</list>
</list>
</list>
<list>
<leaf symbol="divide" />
<leaf symbol="p" />
<list>
<leaf symbol="makeMonic" />
<list>
<leaf symbol="expand" />
<leaf symbol="fp" />
</list>
</list>
</list>
</list>
<list>
<leaf symbol="exit" />
<leaf int="1" />
<list>
<leaf symbol="LET" />
<leaf symbol="p" />
<list>
<leaf symbol="qr" />
<leaf symbol="quotient" />
</list>
</list>
</list>
</list>
</list>
<list>
<leaf symbol="LET" />
<leaf symbol="st" />
<list>
<leaf symbol="sP" />
<leaf symbol="start" />
</list>
</list>
<list>
<leaf symbol="LET" />
<list>
<leaf symbol=":" />
<leaf symbol="G15840040" />
<list>
<leaf symbol="Boolean" />
</list>
</list>
<list>
<leaf symbol="zero?" />
<list>
<leaf symbol="degree" />
<leaf symbol="st" />
</list>
</list>
</list>
<list>
<leaf symbol="exit" />
<leaf int="1" />
<list>
<leaf symbol="IF" />
<leaf symbol="G15840040" />
<leaf symbol="fp" />
<list>
<leaf symbol="SEQ" />
<list>
<leaf symbol="setPoly" />
<leaf symbol="p" />
</list>
<list>
<leaf symbol="LET" />
<list>
<leaf symbol=":" />
<leaf symbol="nm" />
<leaf symbol="R" />
</list>
<leaf symbol="eps" />
</list>
<list>
<leaf symbol=":" />
<leaf symbol="split" />
<list>
<leaf symbol="Record" />
<list>
<leaf symbol=":" />
<leaf symbol="factors" />
<list>
<leaf symbol="List" />
<leaf symbol="UP" />
</list>
</list>
<list>
<leaf symbol=":" />
<leaf symbol="error" />
<leaf symbol="R" />
</list>
</list>
</list>
<list>
<leaf symbol="LET" />
<list>
<leaf symbol=":" />
<leaf symbol="sR" />
<leaf symbol="Rep" />
</list>
<list>
<leaf symbol="::" />
<leaf symbol="st" />
<leaf symbol="Rep" />
</list>
</list>
<list>
<leaf symbol="LET" />
<list>
<leaf symbol=":" />
<leaf symbol="psR" />
<leaf symbol="Rep" />
</list>
<list>
<leaf symbol="^" />
<leaf symbol="sR" />
<list>
<leaf symbol="degree" />
<leaf symbol="poly" />
</list>
</list>
</list>
<list>
<leaf symbol="LET" />
<list>
<leaf symbol=":" />
<leaf symbol="notFoundSplit" />
<list>
<leaf symbol="Boolean" />
</list>
</list>
<leaf symbol="true" />
</list>
<list>
<leaf symbol="REPEAT" />
<list>
<leaf symbol="WHILE" />
<leaf symbol="notFoundSplit" />
</list>
<list>
<leaf symbol="SEQ" />
<list>
<leaf symbol="LET" />
<leaf symbol="psR" />
<list>
<leaf symbol="*" />
<list>
<leaf symbol="*" />
<leaf symbol="psR" />
<leaf symbol="psR" />
</list>
<leaf symbol="sR" />
</list>
</list>
<list>
<leaf symbol="LET" />
<list>
<leaf symbol=":" />
<leaf symbol="tp" />
<leaf symbol="UP" />
</list>
<list>
<leaf symbol="lift" />
<leaf symbol="psR" />
</list>
</list>
<list>
<leaf symbol="LET" />
<list>
<leaf symbol=":" />
<leaf symbol="G15840041" />
<list>
<leaf symbol="Boolean" />
</list>
</list>
<list>
<leaf symbol="zero?" />
<list>
<leaf symbol="degree" />
<leaf symbol="tp" />
</list>
</list>
</list>
<list>
<leaf symbol="exit" />
<leaf int="1" />
<list>
<leaf symbol="IF" />
<leaf symbol="G15840041" />
<list>
<leaf symbol="SEQ" />
<list>
<leaf symbol="IF" />
<leaf symbol="info" />
<list>
<leaf symbol="messagePrint" />
<leaf string="we leave as we got constant factor" />
</list>
<leaf symbol="noBranch" />
</list>
<list>
<leaf symbol="exit" />
<leaf int="1" />
<list>
<list>
<leaf symbol="Sel" />
<list>
<leaf symbol="Factored" />
<leaf symbol="UP" />
</list>
<leaf symbol="nilFactor" />
</list>
<leaf symbol="poly" />
<list>
<leaf symbol="One" />
</list>
</list>
</list>
</list>
<list>
<leaf symbol="SEQ" />
<list>
<leaf symbol="LET" />
<list>
<leaf symbol=":" />
<leaf symbol="splits" />
<list>
<leaf symbol="List" />
<list>
<leaf symbol="Record" />
<list>
<leaf symbol=":" />
<leaf symbol="factors" />
<list>
<leaf symbol="List" />
<leaf symbol="UP" />
</list>
</list>
<list>
<leaf symbol=":" />
<leaf symbol="error" />
<leaf symbol="R" />
</list>
</list>
</list>
</list>
<list>
<leaf symbol="divisorCascade" />
<leaf symbol="p" />
<list>
<leaf symbol="makeMonic" />
<leaf symbol="tp" />
</list>
<leaf symbol="info" />
</list>
</list>
<list>
<leaf symbol="LET" />
<leaf symbol="split" />
<list>
<leaf symbol="reduce" />
<leaf symbol="min" />
<leaf symbol="splits" />
</list>
</list>
<list>
<leaf symbol="exit" />
<leaf int="1" />
<list>
<leaf symbol="LET" />
<leaf symbol="notFoundSplit" />
<list>
<leaf symbol="&lt;=" />
<leaf symbol="eps" />
<list>
<leaf symbol="split" />
<leaf symbol="error" />
</list>
</list>
</list>
</list>
</list>
</list>
</list>
</list>
</list>
<list>
<leaf symbol="REPEAT" />
<list>
<leaf symbol="IN" />
<leaf symbol="fac" />
<list>
<leaf symbol="split" />
<leaf symbol="factors" />
</list>
</list>
<list>
<leaf symbol="LET" />
<leaf symbol="fp" />
<list>
<leaf symbol="SEQ" />
<list>
<leaf symbol="LET" />
<list>
<leaf symbol=":" />
<leaf symbol="G15840042" />
<list>
<leaf symbol="Boolean" />
</list>
</list>
<list>
<leaf symbol="=" />
<list>
<leaf symbol="degree" />
<leaf symbol="fac" />
</list>
<list>
<leaf symbol="One" />
</list>
</list>
</list>
<list>
<leaf symbol="exit" />
<leaf int="1" />
<list>
<leaf symbol="IF" />
<leaf symbol="G15840042" />
<list>
<leaf symbol="*" />
<leaf symbol="fp" />
<list>
<list>
<leaf symbol="Sel" />
<list>
<leaf symbol="Factored" />
<leaf symbol="UP" />
</list>
<leaf symbol="nilFactor" />
</list>
<leaf symbol="fac" />
<list>
<leaf symbol="One" />
</list>
</list>
</list>
<list>
<leaf symbol="*" />
<leaf symbol="fp" />
<list>
<list>
<leaf symbol="Sel" />
<list>
<leaf symbol="Factored" />
<leaf symbol="UP" />
</list>
<leaf symbol="irreducibleFactor" />
</list>
<leaf symbol="fac" />
<list>
<leaf symbol="One" />
</list>
</list>
</list>
</list>
</list>
</list>
</list>
</list>
<list>
<leaf symbol="exit" />
<leaf int="1" />
<leaf symbol="fp" />
</list>
</list>
</list>
</list>
</list>
</list>
<list>
<leaf symbol="DEF" />
<list>
<leaf symbol="startPolynomial" />
<leaf symbol="p" />
</list>
<list>
<list />
<list />
</list>
<list>
<list />
<list />
</list>
<list>
<leaf symbol="SEQ" />
<list>
<leaf symbol="LET" />
<list>
<leaf symbol=":" />
<leaf symbol="fp" />
<list>
<leaf symbol="Factored" />
<leaf symbol="UP" />
</list>
</list>
<list>
<leaf symbol="One" />
</list>
</list>
<list>
<leaf symbol="LET" />
<list>
<leaf symbol=":" />
<leaf symbol="G15840043" />
<list>
<leaf symbol="Boolean" />
</list>
</list>
<list>
<leaf symbol="=" />
<list>
<leaf symbol="degree" />
<leaf symbol="p" />
</list>
<list>
<leaf symbol="One" />
</list>
</list>
</list>
<list>
<leaf symbol="exit" />
<leaf int="1" />
<list>
<leaf symbol="IF" />
<leaf symbol="G15840043" />
<list>
<leaf symbol="SEQ" />
<list>
<leaf symbol="LET" />
<leaf symbol="p" />
<list>
<leaf symbol="makeMonic" />
<leaf symbol="p" />
</list>
</list>
<list>
<leaf symbol="exit" />
<leaf int="1" />
<list>
<leaf symbol="construct" />
<leaf symbol="p" />
<list>
<leaf symbol="irreducibleFactor" />
<leaf symbol="p" />
<list>
<leaf symbol="One" />
</list>
</list>
</list>
</list>
</list>
<list>
<leaf symbol="SEQ" />
<list>
<leaf symbol="LET" />
<list>
<leaf symbol=":" />
<leaf symbol="startPoly" />
<leaf symbol="UP" />
</list>
<list>
<list>
<leaf symbol="Sel" />
<leaf symbol="UP" />
<leaf symbol="monomial" />
</list>
<list>
<leaf symbol="One" />
</list>
<list>
<leaf symbol="One" />
</list>
</list>
</list>
<list>
<leaf symbol="LET" />
<list>
<leaf symbol=":" />
<leaf symbol="eps" />
<leaf symbol="R" />
</list>
<leaf symbol="weakEps" />
</list>
<list>
<leaf symbol="LET" />
<list>
<leaf symbol=":" />
<leaf symbol="r1" />
<leaf symbol="R" />
</list>
<list>
<leaf symbol="rootRadius" />
<leaf symbol="p" />
<leaf symbol="eps" />
</list>
</list>
<list>
<leaf symbol="LET" />
<list>
<leaf symbol=":" />
<leaf symbol="rd" />
<leaf symbol="R" />
</list>
<list>
<leaf symbol="/" />
<list>
<leaf symbol="One" />
</list>
<list>
<leaf symbol="rootRadius" />
<list>
<leaf symbol="reciprocalPolynomial" />
<leaf symbol="p" />
</list>
<leaf symbol="eps" />
</list>
</list>
</list>
<list>
<leaf symbol="LET" />
<list>
<leaf symbol=":" />
<leaf symbol="G15840044" />
<list>
<leaf symbol="Boolean" />
</list>
</list>
<list>
<leaf symbol="&gt;" />
<list>
<leaf symbol="/" />
<leaf symbol="r1" />
<leaf symbol="rd" />
</list>
<list>
<leaf symbol="/" />
<list>
<leaf symbol="::" />
<leaf int="3" />
<leaf symbol="R" />
</list>
<list>
<leaf symbol="::" />
<leaf int="2" />
<leaf symbol="R" />
</list>
</list>
</list>
</list>
<list>
<leaf symbol="exit" />
<leaf int="1" />
<list>
<leaf symbol="IF" />
<leaf symbol="G15840044" />
<list>
<leaf symbol="construct" />
<leaf symbol="startPoly" />
<leaf symbol="fp" />
</list>
<list>
<leaf symbol="SEQ" />
<list>
<leaf symbol="LET" />
<list>
<leaf symbol=":" />
<leaf symbol="u" />
<list>
<leaf symbol="Complex" />
<leaf symbol="R" />
</list>
</list>
<list>
<leaf symbol="schwerpunkt" />
<leaf symbol="p" />
</list>
</list>
<list>
<leaf symbol="LET" />
<leaf symbol="startPoly" />
<list>
<leaf symbol="-" />
<leaf symbol="startPoly" />
<list>
<leaf symbol="monomial" />
<leaf symbol="u" />
<list>
<leaf symbol="Zero" />
</list>
</list>
</list>
</list>
<list>
<leaf symbol="LET" />
<leaf symbol="p" />
<list>
<leaf symbol="shift" />
<leaf symbol="p" />
<list>
<leaf symbol="-" />
<leaf symbol="u" />
</list>
</list>
</list>
<list>
<leaf symbol="LET" />
<list>
<leaf symbol=":" />
<leaf symbol="r1" />
<leaf symbol="R" />
</list>
<list>
<leaf symbol="rootRadius" />
<leaf symbol="p" />
<leaf symbol="eps" />
</list>
</list>
<list>
<leaf symbol="LET" />
<leaf symbol="startPoly" />
<list>
<leaf symbol="/" />
<leaf symbol="startPoly" />
<list>
<leaf symbol="::" />
<leaf symbol="r1" />
<list>
<leaf symbol="Complex" />
<leaf symbol="R" />
</list>
</list>
</list>
</list>
<list>
<leaf symbol="LET" />
<list>
<leaf symbol=":" />
<leaf symbol="listOfCenters" />
<list>
<leaf symbol="List" />
<list>
<leaf symbol="Complex" />
<leaf symbol="R" />
</list>
</list>
</list>
<list>
<leaf symbol="construct" />
<list>
<leaf symbol="complex" />
<leaf symbol="r1" />
<list>
<leaf symbol="Zero" />
</list>
</list>
<list>
<leaf symbol="complex" />
<list>
<leaf symbol="Zero" />
</list>
<leaf symbol="r1" />
</list>
<list>
<leaf symbol="complex" />
<list>
<leaf symbol="-" />
<leaf symbol="r1" />
</list>
<list>
<leaf symbol="Zero" />
</list>
</list>
<list>
<leaf symbol="complex" />
<list>
<leaf symbol="Zero" />
</list>
<list>
<leaf symbol="-" />
<leaf symbol="r1" />
</list>
</list>
</list>
</list>
<list>
<leaf symbol="LET" />
<list>
<leaf symbol=":" />
<leaf symbol="lp" />
<list>
<leaf symbol="List" />
<leaf symbol="UP" />
</list>
</list>
<list>
<leaf symbol="COLLECT" />
<list>
<leaf symbol="IN" />
<leaf symbol="v" />
<leaf symbol="listOfCenters" />
</list>
<list>
<leaf symbol="shift" />
<leaf symbol="p" />
<leaf symbol="v" />
</list>
</list>
</list>
<list>
<leaf symbol="LET" />
<list>
<leaf symbol=":" />
<leaf symbol="centerIsRoot" />
<list>
<leaf symbol="Boolean" />
</list>
</list>
<leaf symbol="false" />
</list>
<list>
<leaf symbol="REPEAT" />
<list>
<leaf symbol="IN" />
<leaf symbol="i" />
<list>
<leaf symbol="SEGMENT" />
<list>
<leaf symbol="One" />
</list>
<list>
<leaf symbol="maxIndex" />
<leaf symbol="lp" />
</list>
</list>
</list>
<list>
<leaf symbol="SEQ" />
<list>
<leaf symbol="LET" />
<leaf symbol="mD" />
<list>
<leaf symbol="minimumDegree" />
<list>
<leaf symbol="lp" />
<leaf symbol="i" />
</list>
</list>
</list>
<list>
<leaf symbol="exit" />
<leaf int="1" />
<list>
<leaf symbol="IF" />
<list>
<leaf symbol="&gt;" />
<leaf symbol="mD" />
<list>
<leaf symbol="Zero" />
</list>
</list>
<list>
<leaf symbol="SEQ" />
<list>
<leaf symbol="LET" />
<list>
<leaf symbol=":" />
<leaf symbol="pp" />
<leaf symbol="UP" />
</list>
<list>
<leaf symbol="-" />
<list>
<leaf symbol="monomial" />
<list>
<leaf symbol="One" />
</list>
<list>
<leaf symbol="One" />
</list>
</list>
<list>
<leaf symbol="monomial" />
<list>
<leaf symbol="-" />
<list>
<leaf symbol="listOfCenters" />
<leaf symbol="i" />
</list>
<leaf symbol="u" />
</list>
<list>
<leaf symbol="Zero" />
</list>
</list>
</list>
</list>
<list>
<leaf symbol="LET" />
<leaf symbol="centerIsRoot" />
<leaf symbol="true" />
</list>
<list>
<leaf symbol="exit" />
<leaf int="1" />
<list>
<leaf symbol="LET" />
<leaf symbol="fp" />
<list>
<leaf symbol="*" />
<leaf symbol="fp" />
<list>
<leaf symbol="irreducibleFactor" />
<leaf symbol="pp" />
<leaf symbol="mD" />
</list>
</list>
</list>
</list>
</list>
<leaf symbol="noBranch" />
</list>
</list>
</list>
</list>
<list>
<leaf symbol="exit" />
<leaf int="1" />
<list>
<leaf symbol="IF" />
<leaf symbol="centerIsRoot" />
<list>
<leaf symbol="SEQ" />
<list>
<leaf symbol="LET" />
<leaf symbol="p" />
<list>
<leaf symbol="quo" />
<list>
<leaf symbol="shift" />
<leaf symbol="p" />
<leaf symbol="u" />
</list>
<list>
<leaf symbol="expand" />
<leaf symbol="fp" />
</list>
</list>
</list>
<list>
<leaf symbol="LET" />
<list>
<leaf symbol=":" />
<leaf symbol="G15840045" />
<list>
<leaf symbol="Boolean" />
</list>
</list>
<list>
<leaf symbol="zero?" />
<list>
<leaf symbol="degree" />
<leaf symbol="p" />
</list>
</list>
</list>
<list>
<leaf symbol="exit" />
<leaf int="1" />
<list>
<leaf symbol="IF" />
<leaf symbol="G15840045" />
<list>
<leaf symbol="construct" />
<leaf symbol="p" />
<leaf symbol="fp" />
</list>
<list>
<leaf symbol="SEQ" />
<list>
<leaf symbol="LET" />
<leaf symbol="sP" />
<list>
<leaf symbol="startPolynomial" />
<leaf symbol="p" />
</list>
</list>
<list>
<leaf symbol="exit" />
<leaf int="1" />
<list>
<leaf symbol="construct" />
<list>
<leaf symbol="sP" />
<leaf symbol="start" />
</list>
<leaf symbol="fp" />
</list>
</list>
</list>
</list>
</list>
</list>
<list>
<leaf symbol="SEQ" />
<list>
<leaf symbol="LET" />
<list>
<leaf symbol=":" />
<leaf symbol="po" />
<list>
<leaf symbol="Integer" />
</list>
</list>
<list>
<leaf symbol="One" />
</list>
</list>
<list>
<leaf symbol="LET" />
<list>
<leaf symbol=":" />
<leaf symbol="maxq" />
<leaf symbol="R" />
</list>
<list>
<leaf symbol="One" />
</list>
</list>
<list>
<leaf symbol="REPEAT" />
<list>
<leaf symbol="IN" />
<leaf symbol="q" />
<leaf symbol="lp" />
</list>
<list>
<leaf symbol="IN" />
<leaf symbol="j" />
<list>
<leaf symbol="SEGMENT" />
<list>
<leaf symbol="One" />
</list>
</list>
</list>
<list>
<leaf symbol="SEQ" />
<list>
<leaf symbol="LET" />
<leaf symbol="r1" />
<list>
<leaf symbol="rootRadius" />
<leaf symbol="q" />
<leaf symbol="eps" />
</list>
</list>
<list>
<leaf symbol="LET" />
<leaf symbol="rd" />
<list>
<leaf symbol="/" />
<list>
<leaf symbol="One" />
</list>
<list>
<leaf symbol="rootRadius" />
<list>
<leaf symbol="reciprocalPolynomial" />
<leaf symbol="q" />
</list>
<leaf symbol="eps" />
</list>
</list>
</list>
<list>
<leaf symbol="LET" />
<list>
<leaf symbol=":" />
<leaf symbol="G15840046" />
<list>
<leaf symbol="Boolean" />
</list>
</list>
<list>
<leaf symbol="&gt;" />
<list>
<leaf symbol="LET" />
<leaf symbol="qq" />
<list>
<leaf symbol="/" />
<leaf symbol="r1" />
<leaf symbol="rd" />
</list>
</list>
<list>
<leaf symbol="/" />
<list>
<leaf symbol="::" />
<leaf int="3" />
<leaf symbol="R" />
</list>
<list>
<leaf symbol="::" />
<leaf int="2" />
<leaf symbol="R" />
</list>
</list>
</list>
</list>
<list>
<leaf symbol="exit" />
<leaf int="1" />
<list>
<leaf symbol="IF" />
<leaf symbol="G15840046" />
<list>
<leaf symbol="SEQ" />
<list>
<leaf symbol="LET" />
<leaf symbol="po" />
<leaf symbol="j" />
</list>
<list>
<leaf symbol="exit" />
<leaf int="1" />
<list>
<leaf symbol="leave" />
<leaf int="1" />
<leaf symbol="$NoValue" />
</list>
</list>
</list>
<list>
<leaf symbol="SEQ" />
<list>
<leaf symbol="IF" />
<list>
<leaf symbol="=" />
<leaf symbol="j" />
<list>
<leaf symbol="One" />
</list>
</list>
<list>
<leaf symbol="LET" />
<leaf symbol="maxq" />
<leaf symbol="qq" />
</list>
<leaf symbol="noBranch" />
</list>
<list>
<leaf symbol="exit" />
<leaf int="1" />
<list>
<leaf symbol="IF" />
<list>
<leaf symbol="&gt;" />
<leaf symbol="qq" />
<leaf symbol="maxq" />
</list>
<list>
<leaf symbol="SEQ" />
<list>
<leaf symbol="LET" />
<leaf symbol="maxq" />
<leaf symbol="qq" />
</list>
<list>
<leaf symbol="exit" />
<leaf int="1" />
<list>
<leaf symbol="LET" />
<leaf symbol="po" />
<leaf symbol="j" />
</list>
</list>
</list>
<leaf symbol="noBranch" />
</list>
</list>
</list>
</list>
</list>
</list>
</list>
<list>
<leaf symbol="exit" />
<leaf int="1" />
<list>
<leaf symbol="construct" />
<list>
<leaf symbol="-" />
<leaf symbol="startPoly" />
<list>
<leaf symbol="monomial" />
<list>
<leaf symbol="listOfCenters" />
<leaf symbol="po" />
</list>
<list>
<leaf symbol="Zero" />
</list>
</list>
</list>
<leaf symbol="fp" />
</list>
</list>
</list>
</list>
</list>
</list>
</list>
</list>
</list>
</list>
</list>
</list>
</list>
<list>
<leaf symbol="DEF" />
<list>
<leaf symbol="norm" />
<leaf symbol="p" />
</list>
<list>
<list />
<list />
</list>
<list>
<list />
<list />
</list>
<list>
<leaf symbol="SEQ" />
<list>
<leaf symbol="LET" />
<list>
<leaf symbol=":" />
<leaf symbol="nm" />
<leaf symbol="R" />
</list>
<list>
<leaf symbol="Zero" />
</list>
</list>
<list>
<leaf symbol="REPEAT" />
<list>
<leaf symbol="IN" />
<leaf symbol="c" />
<list>
<leaf symbol="coefficients" />
<leaf symbol="p" />
</list>
</list>
<list>
<leaf symbol="LET" />
<leaf symbol="nm" />
<list>
<leaf symbol="+" />
<leaf symbol="nm" />
<list>
<leaf symbol="absC" />
<leaf symbol="c" />
</list>
</list>
</list>
</list>
<list>
<leaf symbol="exit" />
<leaf int="1" />
<leaf symbol="nm" />
</list>
</list>
</list>
<list>
<leaf symbol="DEF" />
<list>
<leaf symbol="pleskenSplit" />
<leaf symbol="poly" />
<leaf symbol="eps" />
</list>
<list>
<list />
<list />
<list />
</list>
<list>
<list />
<list />
<list />
</list>
<list>
<leaf symbol="pleskenSplit" />
<leaf symbol="poly" />
<leaf symbol="eps" />
<leaf symbol="false" />
</list>
</list>
<list>
<leaf symbol="DEF" />
<list>
<leaf symbol="graeffe" />
<leaf symbol="p" />
</list>
<list>
<list />
<list />
</list>
<list>
<list />
<list />
</list>
<list>
<leaf symbol="SEQ" />
<list>
<leaf symbol="LET" />
<list>
<leaf symbol=":" />
<leaf symbol="n" />
<list>
<leaf symbol="NonNegativeInteger" />
</list>
</list>
<list>
<leaf symbol="degree" />
<leaf symbol="p" />
</list>
</list>
<list>
<leaf symbol="LET" />
<list>
<leaf symbol=":" />
<leaf symbol="aForth" />
<list>
<leaf symbol="List" />
<list>
<leaf symbol="Complex" />
<leaf symbol="R" />
</list>
</list>
</list>
<list>
<leaf symbol="construct" />
</list>
</list>
<list>
<leaf symbol="REPEAT" />
<list>
<leaf symbol="IN" />
<leaf symbol="k" />
<list>
<leaf symbol="SEGMENT" />
<list>
<leaf symbol="Zero" />
</list>
<leaf symbol="n" />
</list>
</list>
<list>
<leaf symbol="LET" />
<leaf symbol="aForth" />
<list>
<leaf symbol="cons" />
<list>
<leaf symbol="coefficient" />
<leaf symbol="p" />
<list>
<leaf symbol="::" />
<leaf symbol="k" />
<list>
<leaf symbol="NonNegativeInteger" />
</list>
</list>
</list>
<leaf symbol="aForth" />
</list>
</list>
</list>
<list>
<leaf symbol="LET" />
<list>
<leaf symbol=":" />
<leaf symbol="aBack" />
<list>
<leaf symbol="List" />
<list>
<leaf symbol="Complex" />
<leaf symbol="R" />
</list>
</list>
</list>
<list>
<leaf symbol="construct" />
</list>
</list>
<list>
<leaf symbol="LET" />
<list>
<leaf symbol=":" />
<leaf symbol="gp" />
<leaf symbol="UP" />
</list>
<list>
<leaf symbol="Sel" />
<leaf symbol="UP" />
<list>
<leaf symbol="Zero" />
</list>
</list>
</list>
<list>
<leaf symbol="REPEAT" />
<list>
<leaf symbol="IN" />
<leaf symbol="k" />
<list>
<leaf symbol="SEGMENT" />
<list>
<leaf symbol="Zero" />
</list>
<leaf symbol="n" />
</list>
</list>
<list>
<leaf symbol="SEQ" />
<list>
<leaf symbol="LET" />
<list>
<leaf symbol=":" />
<leaf symbol="ak" />
<list>
<leaf symbol="Complex" />
<leaf symbol="R" />
</list>
</list>
<list>
<leaf symbol="first" />
<leaf symbol="aForth" />
</list>
</list>
<list>
<leaf symbol="LET" />
<leaf symbol="aForth" />
<list>
<leaf symbol="rest" />
<leaf symbol="aForth" />
</list>
</list>
<list>
<leaf symbol="LET" />
<list>
<leaf symbol=":" />
<leaf symbol="aForthCopy" />
<list>
<leaf symbol="List" />
<list>
<leaf symbol="Complex" />
<leaf symbol="R" />
</list>
</list>
</list>
<leaf symbol="aForth" />
</list>
<list>
<leaf symbol="LET" />
<list>
<leaf symbol=":" />
<leaf symbol="aBackCopy" />
<list>
<leaf symbol="List" />
<list>
<leaf symbol="Complex" />
<leaf symbol="R" />
</list>
</list>
</list>
<leaf symbol="aBack" />
</list>
<list>
<leaf symbol="LET" />
<list>
<leaf symbol=":" />
<leaf symbol="sum" />
<list>
<leaf symbol="Complex" />
<leaf symbol="R" />
</list>
</list>
<list>
<leaf symbol="Zero" />
</list>
</list>
<list>
<leaf symbol="LET" />
<list>
<leaf symbol=":" />
<leaf symbol="const" />
<list>
<leaf symbol="Integer" />
</list>
</list>
<list>
<leaf symbol="-" />
<list>
<leaf symbol="One" />
</list>
</list>
</list>
<list>
<leaf symbol="REPEAT" />
<list>
<leaf symbol="IN" />
<leaf symbol="aminus" />
<leaf symbol="aBack" />
</list>
<list>
<leaf symbol="IN" />
<leaf symbol="aplus" />
<leaf symbol="aForth" />
</list>
<list>
<leaf symbol="SEQ" />
<list>
<leaf symbol="LET" />
<leaf symbol="sum" />
<list>
<leaf symbol="+" />
<leaf symbol="sum" />
<list>
<leaf symbol="*" />
<list>
<leaf symbol="*" />
<leaf symbol="const" />
<leaf symbol="aminus" />
</list>
<leaf symbol="aplus" />
</list>
</list>
</list>
<list>
<leaf symbol="LET" />
<leaf symbol="aForthCopy" />
<list>
<leaf symbol="rest" />
<leaf symbol="aForthCopy" />
</list>
</list>
<list>
<leaf symbol="LET" />
<leaf symbol="aBackCopy" />
<list>
<leaf symbol="rest" />
<leaf symbol="aBackCopy" />
</list>
</list>
<list>
<leaf symbol="exit" />
<leaf int="1" />
<list>
<leaf symbol="LET" />
<leaf symbol="const" />
<list>
<leaf symbol="-" />
<leaf symbol="const" />
</list>
</list>
</list>
</list>
</list>
<list>
<leaf symbol="LET" />
<leaf symbol="gp" />
<list>
<leaf symbol="+" />
<leaf symbol="gp" />
<list>
<leaf symbol="monomial" />
<list>
<leaf symbol="+" />
<list>
<leaf symbol="*" />
<leaf symbol="ak" />
<leaf symbol="ak" />
</list>
<list>
<leaf symbol="*" />
<leaf int="2" />
<leaf symbol="sum" />
</list>
</list>
<list>
<leaf symbol="::" />
<list>
<leaf symbol="-" />
<leaf symbol="n" />
<leaf symbol="k" />
</list>
<list>
<leaf symbol="NonNegativeInteger" />
</list>
</list>
</list>
</list>
</list>
<list>
<leaf symbol="exit" />
<leaf int="1" />
<list>
<leaf symbol="LET" />
<leaf symbol="aBack" />
<list>
<leaf symbol="cons" />
<leaf symbol="ak" />
<leaf symbol="aBack" />
</list>
</list>
</list>
</list>
</list>
<list>
<leaf symbol="exit" />
<leaf int="1" />
<leaf symbol="gp" />
</list>
</list>
</list>
<list>
<leaf symbol="DEF" />
<list>
<leaf symbol="rootRadius" />
<leaf symbol="p" />
<leaf symbol="errorQuotient" />
</list>
<list>
<list />
<list />
<list />
</list>
<list>
<list />
<list />
<list />
</list>
<list>
<leaf symbol="SEQ" />
<list>
<leaf symbol="LET" />
<list>
<leaf symbol=":" />
<leaf symbol="G15840047" />
<list>
<leaf symbol="Boolean" />
</list>
</list>
<list>
<leaf symbol="&lt;=" />
<leaf symbol="errorQuotient" />
<list>
<leaf symbol="Sel" />
<leaf symbol="R" />
<list>
<leaf symbol="One" />
</list>
</list>
</list>
</list>
<list>
<leaf symbol="exit" />
<leaf int="1" />
<list>
<leaf symbol="IF" />
<leaf symbol="G15840047" />
<list>
<leaf symbol="error" />
<leaf string="rootRadius: second Parameter must be greater than 1" />
</list>
<list>
<leaf symbol="SEQ" />
<list>
<leaf symbol="LET" />
<list>
<leaf symbol=":" />
<leaf symbol="pp" />
<leaf symbol="UP" />
</list>
<leaf symbol="p" />
</list>
<list>
<leaf symbol="LET" />
<list>
<leaf symbol=":" />
<leaf symbol="rho" />
<leaf symbol="R" />
</list>
<list>
<leaf symbol="calculateScale" />
<list>
<leaf symbol="makeMonic" />
<leaf symbol="pp" />
</list>
</list>
</list>
<list>
<leaf symbol="LET" />
<list>
<leaf symbol=":" />
<leaf symbol="rR" />
<leaf symbol="R" />
</list>
<leaf symbol="rho" />
</list>
<list>
<leaf symbol="LET" />
<leaf symbol="pp" />
<list>
<leaf symbol="makeMonic" />
<list>
<leaf symbol="scale" />
<leaf symbol="pp" />
<list>
<leaf symbol="complex" />
<leaf symbol="rho" />
<list>
<leaf symbol="Sel" />
<leaf symbol="R" />
<list>
<leaf symbol="Zero" />
</list>
</list>
</list>
</list>
</list>
</list>
<list>
<leaf symbol="LET" />
<list>
<leaf symbol=":" />
<leaf symbol="expo" />
<list>
<leaf symbol="NonNegativeInteger" />
</list>
</list>
<list>
<leaf symbol="One" />
</list>
</list>
<list>
<leaf symbol="LET" />
<list>
<leaf symbol=":" />
<leaf symbol="d" />
<list>
<leaf symbol="NonNegativeInteger" />
</list>
</list>
<list>
<leaf symbol="degree" />
<leaf symbol="p" />
</list>
</list>
<list>
<leaf symbol="LET" />
<list>
<leaf symbol=":" />
<leaf symbol="currentError" />
<leaf symbol="R" />
</list>
<list>
<leaf symbol="nthRoot" />
<list>
<leaf symbol="::" />
<leaf int="2" />
<leaf symbol="R" />
</list>
<leaf int="2" />
</list>
</list>
<list>
<leaf symbol="LET" />
<leaf symbol="currentError" />
<list>
<leaf symbol="*" />
<list>
<leaf symbol="*" />
<leaf symbol="d" />
<leaf int="20" />
</list>
<leaf symbol="currentError" />
</list>
</list>
<list>
<leaf symbol="REPEAT" />
<list>
<leaf symbol="WHILE" />
<list>
<leaf symbol="&gt;=" />
<leaf symbol="currentError" />
<leaf symbol="errorQuotient" />
</list>
</list>
<list>
<leaf symbol="SEQ" />
<list>
<leaf symbol="LET" />
<leaf symbol="pp" />
<list>
<leaf symbol="graeffe" />
<leaf symbol="pp" />
</list>
</list>
<list>
<leaf symbol="LET" />
<leaf symbol="rho" />
<list>
<leaf symbol="calculateScale" />
<leaf symbol="pp" />
</list>
</list>
<list>
<leaf symbol="LET" />
<leaf symbol="expo" />
<list>
<leaf symbol="*" />
<leaf int="2" />
<leaf symbol="expo" />
</list>
</list>
<list>
<leaf symbol="LET" />
<leaf symbol="errorQuotient" />
<list>
<leaf symbol="*" />
<leaf symbol="errorQuotient" />
<leaf symbol="errorQuotient" />
</list>
</list>
<list>
<leaf symbol="LET" />
<leaf symbol="rR" />
<list>
<leaf symbol="*" />
<list>
<leaf symbol="nthRoot" />
<leaf symbol="rho" />
<leaf symbol="expo" />
</list>
<leaf symbol="rR" />
</list>
</list>
<list>
<leaf symbol="exit" />
<leaf int="1" />
<list>
<leaf symbol="LET" />
<leaf symbol="pp" />
<list>
<leaf symbol="makeMonic" />
<list>
<leaf symbol="scale" />
<leaf symbol="pp" />
<list>
<leaf symbol="complex" />
<leaf symbol="rho" />
<list>
<leaf symbol="Sel" />
<leaf symbol="R" />
<list>
<leaf symbol="Zero" />
</list>
</list>
</list>
</list>
</list>
</list>
</list>
</list>
</list>
<list>
<leaf symbol="exit" />
<leaf int="1" />
<leaf symbol="rR" />
</list>
</list>
</list>
</list>
</list>
</list>
<list>
<leaf symbol="DEF" />
<list>
<leaf symbol="rootRadius" />
<leaf symbol="p" />
</list>
<list>
<list />
<list />
</list>
<list>
<list />
<list />
</list>
<list>
<leaf symbol="rootRadius" />
<leaf symbol="p" />
<list>
<leaf symbol="+" />
<list>
<leaf symbol="One" />
</list>
<leaf symbol="globalEps" />
</list>
</list>
</list>
<list>
<leaf symbol="DEF" />
<list>
<leaf symbol="schwerpunkt" />
<leaf symbol="p" />
</list>
<list>
<list />
<list />
</list>
<list>
<list />
<list />
</list>
<list>
<leaf symbol="SEQ" />
<list>
<leaf symbol="LET" />
<list>
<leaf symbol=":" />
<leaf symbol="G15840048" />
<list>
<leaf symbol="Boolean" />
</list>
</list>
<list>
<leaf symbol="zero?" />
<leaf symbol="p" />
</list>
</list>
<list>
<leaf symbol="exit" />
<leaf int="1" />
<list>
<leaf symbol="IF" />
<leaf symbol="G15840048" />
<list>
<leaf symbol="Sel" />
<list>
<leaf symbol="Complex" />
<leaf symbol="R" />
</list>
<list>
<leaf symbol="Zero" />
</list>
</list>
<list>
<leaf symbol="SEQ" />
<list>
<leaf symbol="LET" />
<list>
<leaf symbol=":" />
<leaf symbol="G15840049" />
<list>
<leaf symbol="Boolean" />
</list>
</list>
<list>
<leaf symbol="zero?" />
<list>
<leaf symbol="LET" />
<leaf symbol="d" />
<list>
<leaf symbol="degree" />
<leaf symbol="p" />
</list>
</list>
</list>
</list>
<list>
<leaf symbol="exit" />
<leaf int="1" />
<list>
<leaf symbol="IF" />
<leaf symbol="G15840049" />
<list>
<leaf symbol="error" />
<leaf string="schwerpunkt: non-zero const. polynomial has no roots and no schwerpunkt" />
</list>
<list>
<leaf symbol="SEQ" />
<list>
<leaf symbol="LET" />
<list>
<leaf symbol=":" />
<leaf symbol="lC" />
<list>
<leaf symbol="Complex" />
<leaf symbol="R" />
</list>
</list>
<list>
<leaf symbol="coefficient" />
<leaf symbol="p" />
<leaf symbol="d" />
</list>
</list>
<list>
<leaf symbol="LET" />
<list>
<leaf symbol=":" />
<leaf symbol="nC" />
<list>
<leaf symbol="Complex" />
<leaf symbol="R" />
</list>
</list>
<list>
<leaf symbol="coefficient" />
<leaf symbol="p" />
<list>
<leaf symbol="pretend" />
<list>
<leaf symbol="-" />
<leaf symbol="d" />
<list>
<leaf symbol="One" />
</list>
</list>
<list>
<leaf symbol="NonNegativeInteger" />
</list>
</list>
</list>
</list>
<list>
<leaf symbol="LET" />
<leaf symbol="denom" />
<list>
<leaf symbol="recip" />
<list>
<leaf symbol="*" />
<list>
<leaf symbol="::" />
<list>
<leaf symbol="::" />
<leaf symbol="d" />
<list>
<leaf symbol="Integer" />
</list>
</list>
<list>
<leaf symbol="Complex" />
<leaf symbol="R" />
</list>
</list>
<leaf symbol="lC" />
</list>
</list>
</list>
<list>
<leaf symbol="exit" />
<leaf int="1" />
<list>
<leaf symbol="IF" />
<list>
<leaf symbol="case" />
<leaf symbol="denom" />
<leaf string="failed" />
</list>
<list>
<leaf symbol="error" />
<leaf string="schwerpunkt:          degree * leadingCoefficient not invertible in ring of coefficients" />
</list>
<list>
<leaf symbol="-" />
<list>
<leaf symbol="*" />
<leaf symbol="nC" />
<list>
<leaf symbol="::" />
<leaf symbol="denom" />
<list>
<leaf symbol="Complex" />
<leaf symbol="R" />
</list>
</list>
</list>
</list>
</list>
</list>
</list>
</list>
</list>
</list>
</list>
</list>
</list>
</list>
<list>
<leaf symbol="DEF" />
<list>
<leaf symbol="reciprocalPolynomial" />
<leaf symbol="p" />
</list>
<list>
<list />
<list />
</list>
<list>
<list />
<list />
</list>
<list>
<leaf symbol="SEQ" />
<list>
<leaf symbol="LET" />
<list>
<leaf symbol=":" />
<leaf symbol="G15840050" />
<list>
<leaf symbol="Boolean" />
</list>
</list>
<list>
<leaf symbol="zero?" />
<leaf symbol="p" />
</list>
</list>
<list>
<leaf symbol="exit" />
<leaf int="1" />
<list>
<leaf symbol="IF" />
<leaf symbol="G15840050" />
<list>
<leaf symbol="Zero" />
</list>
<list>
<leaf symbol="SEQ" />
<list>
<leaf symbol="LET" />
<list>
<leaf symbol=":" />
<leaf symbol="d" />
<list>
<leaf symbol="NonNegativeInteger" />
</list>
</list>
<list>
<leaf symbol="degree" />
<leaf symbol="p" />
</list>
</list>
<list>
<leaf symbol="LET" />
<list>
<leaf symbol=":" />
<leaf symbol="md" />
<list>
<leaf symbol="NonNegativeInteger" />
</list>
</list>
<list>
<leaf symbol="+" />
<leaf symbol="d" />
<list>
<leaf symbol="minimumDegree" />
<leaf symbol="p" />
</list>
</list>
</list>
<list>
<leaf symbol="LET" />
<list>
<leaf symbol=":" />
<leaf symbol="lm" />
<list>
<leaf symbol="List" />
<leaf symbol="UP" />
</list>
</list>
<list>
<leaf symbol="COLLECT" />
<list>
<leaf symbol="IN" />
<leaf symbol="i" />
<list>
<leaf symbol="SEGMENT" />
<list>
<leaf symbol="Zero" />
</list>
<leaf symbol="d" />
</list>
</list>
<list>
<leaf symbol="monomial" />
<list>
<leaf symbol="coefficient" />
<leaf symbol="p" />
<leaf symbol="i" />
</list>
<list>
<leaf symbol="::" />
<list>
<leaf symbol="-" />
<leaf symbol="md" />
<leaf symbol="i" />
</list>
<list>
<leaf symbol="NonNegativeInteger" />
</list>
</list>
</list>
</list>
</list>
<list>
<leaf symbol="exit" />
<leaf int="1" />
<list>
<leaf symbol="LET" />
<leaf symbol="sol" />
<list>
<leaf symbol="reduce" />
<leaf symbol="+" />
<leaf symbol="lm" />
</list>
</list>
</list>
</list>
</list>
</list>
</list>
</list>
<list>
<leaf symbol="DEF" />
<list>
<leaf symbol="divisorCascade" />
<leaf symbol="p" />
<leaf symbol="tp" />
<leaf symbol="info" />
</list>
<list>
<list />
<list />
<list />
<list />
</list>
<list>
<list />
<list />
<list />
<list />
</list>
<list>
<leaf symbol="SEQ" />
<list>
<leaf symbol="LET" />
<list>
<leaf symbol=":" />
<leaf symbol="lfae" />
<list>
<leaf symbol="List" />
<list>
<leaf symbol="Record" />
<list>
<leaf symbol=":" />
<leaf symbol="factors" />
<list>
<leaf symbol="List" />
<leaf symbol="UP" />
</list>
</list>
<list>
<leaf symbol=":" />
<leaf symbol="error" />
<leaf symbol="R" />
</list>
</list>
</list>
</list>
<list>
<leaf symbol="construct" />
</list>
</list>
<list>
<leaf symbol="REPEAT" />
<list>
<leaf symbol="IN" />
<leaf symbol="i" />
<list>
<leaf symbol="SEGMENT" />
<list>
<leaf symbol="One" />
</list>
<list>
<leaf symbol="degree" />
<leaf symbol="tp" />
</list>
</list>
</list>
<list>
<leaf symbol="WHILE" />
<list>
<leaf symbol="&gt;" />
<list>
<leaf symbol="degree" />
<leaf symbol="tp" />
</list>
<list>
<leaf symbol="Zero" />
</list>
</list>
</list>
<list>
<leaf symbol="SEQ" />
<list>
<leaf symbol="LET" />
<list>
<leaf symbol=":" />
<leaf symbol="qr" />
<list>
<leaf symbol="Record" />
<list>
<leaf symbol=":" />
<leaf symbol="quotient" />
<leaf symbol="UP" />
</list>
<list>
<leaf symbol=":" />
<leaf symbol="remainder" />
<leaf symbol="UP" />
</list>
</list>
</list>
<list>
<leaf symbol="divide" />
<leaf symbol="p" />
<leaf symbol="tp" />
</list>
</list>
<list>
<leaf symbol="LET" />
<list>
<leaf symbol=":" />
<leaf symbol="factor1" />
<leaf symbol="UP" />
</list>
<leaf symbol="tp" />
</list>
<list>
<leaf symbol="LET" />
<list>
<leaf symbol=":" />
<leaf symbol="factor2" />
<leaf symbol="UP" />
</list>
<list>
<leaf symbol="makeMonic" />
<list>
<leaf symbol="qr" />
<leaf symbol="quotient" />
</list>
</list>
</list>
<list>
<leaf symbol="LET" />
<leaf symbol="tp" />
<list>
<leaf symbol="qr" />
<leaf symbol="remainder" />
</list>
</list>
<list>
<leaf symbol="LET" />
<list>
<leaf symbol=":" />
<leaf symbol="nm" />
<leaf symbol="R" />
</list>
<list>
<leaf symbol="norm" />
<leaf symbol="tp" />
</list>
</list>
<list>
<leaf symbol="LET" />
<list>
<leaf symbol=":" />
<leaf symbol="listOfFactors" />
<list>
<leaf symbol="List" />
<leaf symbol="UP" />
</list>
</list>
<list>
<leaf symbol="cons" />
<leaf symbol="factor2" />
<list>
<list>
<leaf symbol="Sel" />
<list>
<leaf symbol="List" />
<leaf symbol="UP" />
</list>
<leaf symbol="construct" />
</list>
</list>
</list>
</list>
<list>
<leaf symbol="LET" />
<leaf symbol="listOfFactors" />
<list>
<leaf symbol="cons" />
<leaf symbol="factor1" />
<leaf symbol="listOfFactors" />
</list>
</list>
<list>
<leaf symbol="LET" />
<leaf symbol="lfae" />
<list>
<leaf symbol="cons" />
<list>
<leaf symbol="construct" />
<leaf symbol="listOfFactors" />
<leaf symbol="nm" />
</list>
<leaf symbol="lfae" />
</list>
</list>
<list>
<leaf symbol="exit" />
<leaf int="1" />
<list>
<leaf symbol="IF" />
<leaf symbol="info" />
<list>
<leaf symbol="SEQ" />
<list>
<leaf symbol="print" />
<leaf symbol="emptyLine" />
</list>
<list>
<leaf symbol="LET" />
<list>
<leaf symbol=":" />
<leaf symbol="lof" />
<list>
<leaf symbol="List" />
<list>
<leaf symbol="OutputForm" />
</list>
</list>
</list>
<list>
<leaf symbol="construct" />
<list>
<leaf symbol="message" />
<leaf string="error polynomial has degree " />
</list>
<list>
<leaf symbol="::" />
<list>
<leaf symbol="degree" />
<leaf symbol="tp" />
</list>
<list>
<leaf symbol="OutputForm" />
</list>
</list>
<list>
<leaf symbol="message" />
<leaf string=" and norm " />
</list>
<list>
<leaf symbol="::" />
<leaf symbol="nm" />
<list>
<leaf symbol="OutputForm" />
</list>
</list>
</list>
</list>
<list>
<leaf symbol="print" />
<list>
<leaf symbol="center" />
<list>
<leaf symbol="hconcat" />
<leaf symbol="lof" />
</list>
</list>
</list>
<list>
<leaf symbol="LET" />
<list>
<leaf symbol=":" />
<leaf symbol="lof" />
<list>
<leaf symbol="List" />
<list>
<leaf symbol="OutputForm" />
</list>
</list>
</list>
<list>
<leaf symbol="construct" />
<list>
<leaf symbol="message" />
<leaf string="degrees of factors:" />
</list>
<list>
<leaf symbol="::" />
<list>
<leaf symbol="degree" />
<leaf symbol="factor1" />
</list>
<list>
<leaf symbol="OutputForm" />
</list>
</list>
<list>
<leaf symbol="message" />
<leaf string="  " />
</list>
<list>
<leaf symbol="::" />
<list>
<leaf symbol="degree" />
<leaf symbol="factor2" />
</list>
<list>
<leaf symbol="OutputForm" />
</list>
</list>
</list>
</list>
<list>
<leaf symbol="exit" />
<leaf int="1" />
<list>
<leaf symbol="print" />
<list>
<leaf symbol="center" />
<list>
<leaf symbol="hconcat" />
<leaf symbol="lof" />
</list>
</list>
</list>
</list>
</list>
<leaf symbol="noBranch" />
</list>
</list>
</list>
</list>
<list>
<leaf symbol="IF" />
<leaf symbol="info" />
<list>
<leaf symbol="print" />
<leaf symbol="emptyLine" />
</list>
<leaf symbol="noBranch" />
</list>
<list>
<leaf symbol="exit" />
<leaf int="1" />
<list>
<leaf symbol="reverse" />
<leaf symbol="lfae" />
</list>
</list>
</list>
</list>
<list>
<leaf symbol="DEF" />
<list>
<leaf symbol="divisorCascade" />
<leaf symbol="p" />
<leaf symbol="tp" />
</list>
<list>
<list />
<list />
<list />
</list>
<list>
<list />
<list />
<list />
</list>
<list>
<leaf symbol="divisorCascade" />
<leaf symbol="p" />
<leaf symbol="tp" />
<leaf symbol="false" />
</list>
</list>
<list>
<leaf symbol="DEF" />
<list>
<leaf symbol="factor" />
<leaf symbol="poly" />
<leaf symbol="eps" />
</list>
<list>
<list />
<list />
<list />
</list>
<list>
<list />
<list />
<list />
</list>
<list>
<leaf symbol="factor" />
<leaf symbol="poly" />
<leaf symbol="eps" />
<leaf symbol="false" />
</list>
</list>
<list>
<leaf symbol="DEF" />
<list>
<leaf symbol="factor" />
<leaf symbol="p" />
</list>
<list>
<list />
<list />
</list>
<list>
<list />
<list />
</list>
<list>
<leaf symbol="factor" />
<leaf symbol="p" />
<leaf symbol="globalEps" />
</list>
</list>
<list>
<leaf symbol="DEF" />
<list>
<leaf symbol="factor" />
<leaf symbol="poly" />
<leaf symbol="eps" />
<leaf symbol="info" />
</list>
<list>
<list />
<list />
<list />
<list />
</list>
<list>
<list />
<list />
<list />
<list />
</list>
<list>
<leaf symbol="SEQ" />
<list>
<leaf symbol="LET" />
<list>
<leaf symbol=":" />
<leaf symbol="result" />
<list>
<leaf symbol="Factored" />
<leaf symbol="UP" />
</list>
</list>
<list>
<leaf symbol="coerce" />
<list>
<leaf symbol="monomial" />
<list>
<leaf symbol="leadingCoefficient" />
<leaf symbol="poly" />
</list>
<list>
<leaf symbol="Zero" />
</list>
</list>
</list>
</list>
<list>
<leaf symbol="LET" />
<list>
<leaf symbol=":" />
<leaf symbol="d" />
<list>
<leaf symbol="NonNegativeInteger" />
</list>
</list>
<list>
<leaf symbol="degree" />
<leaf symbol="poly" />
</list>
</list>
<list>
<leaf symbol="LET" />
<list>
<leaf symbol=":" />
<leaf symbol="eps0" />
<leaf symbol="R" />
</list>
<list>
<leaf symbol="/" />
<leaf symbol="eps" />
<list>
<leaf symbol="*" />
<leaf symbol="ten" />
<leaf symbol="ten" />
</list>
</list>
</list>
<list>
<leaf symbol="exit" />
<leaf int="1" />
<list>
<leaf symbol="IF" />
<list>
<leaf symbol="=" />
<leaf symbol="d" />
<list>
<leaf symbol="One" />
</list>
</list>
<list>
<list>
<leaf symbol="Sel" />
<list>
<leaf symbol="Factored" />
<leaf symbol="UP" />
</list>
<leaf symbol="irreducibleFactor" />
</list>
<leaf symbol="poly" />
<list>
<leaf symbol="One" />
</list>
</list>
<list>
<leaf symbol="SEQ" />
<list>
<leaf symbol="LET" />
<list>
<leaf symbol=":" />
<leaf symbol="listOfFactors" />
<list>
<leaf symbol="List" />
<list>
<leaf symbol="Record" />
<list>
<leaf symbol=":" />
<leaf symbol="factor" />
<leaf symbol="UP" />
</list>
<list>
<leaf symbol=":" />
<leaf symbol="exponent" />
<list>
<leaf symbol="Integer" />
</list>
</list>
</list>
</list>
</list>
<list>
<leaf symbol="list" />
<list>
<leaf symbol="construct" />
<list>
<leaf symbol="makeMonic" />
<leaf symbol="poly" />
</list>
<list>
<leaf symbol="One" />
</list>
</list>
</list>
</list>
<list>
<leaf symbol="IF" />
<leaf symbol="info" />
<list>
<leaf symbol="SEQ" />
<list>
<leaf symbol="LET" />
<list>
<leaf symbol=":" />
<leaf symbol="lof" />
<list>
<leaf symbol="List" />
<list>
<leaf symbol="OutputForm" />
</list>
</list>
</list>
<list>
<leaf symbol="construct" />
<leaf symbol="dashes" />
<leaf symbol="dots" />
<list>
<leaf symbol="message" />
<leaf string="list of Factors:" />
</list>
<leaf symbol="dots" />
<list>
<leaf symbol="::" />
<leaf symbol="listOfFactors" />
<list>
<leaf symbol="OutputForm" />
</list>
</list>
<leaf symbol="dashes" />
<list>
<leaf symbol="message" />
<leaf string="list of Linear Factors:" />
</list>
<leaf symbol="dots" />
<list>
<leaf symbol="::" />
<leaf symbol="result" />
<list>
<leaf symbol="OutputForm" />
</list>
</list>
<leaf symbol="dots" />
<leaf symbol="dashes" />
</list>
</list>
<list>
<leaf symbol="exit" />
<leaf int="1" />
<list>
<leaf symbol="print" />
<list>
<leaf symbol="vconcat" />
<leaf symbol="lof" />
</list>
</list>
</list>
</list>
<leaf symbol="noBranch" />
</list>
<list>
<leaf symbol="REPEAT" />
<list>
<leaf symbol="WHILE" />
<list>
<leaf symbol="SEQ" />
<list>
<leaf symbol="LET" />
<list>
<leaf symbol=":" />
<leaf symbol="G15840051" />
<list>
<leaf symbol="Boolean" />
</list>
</list>
<list>
<leaf symbol="empty?" />
<leaf symbol="listOfFactors" />
</list>
</list>
<list>
<leaf symbol="exit" />
<leaf int="1" />
<list>
<leaf symbol="IF" />
<leaf symbol="G15840051" />
<leaf symbol="false" />
<leaf symbol="true" />
</list>
</list>
</list>
</list>
<list>
<leaf symbol="SEQ" />
<list>
<leaf symbol="LET" />
<list>
<leaf symbol=":" />
<leaf symbol="p" />
<leaf symbol="UP" />
</list>
<list>
<list>
<leaf symbol="first" />
<leaf symbol="listOfFactors" />
</list>
<leaf symbol="factor" />
</list>
</list>
<list>
<leaf symbol="LET" />
<list>
<leaf symbol=":" />
<leaf symbol="exponentOfp" />
<list>
<leaf symbol="Integer" />
</list>
</list>
<list>
<list>
<leaf symbol="first" />
<leaf symbol="listOfFactors" />
</list>
<leaf symbol="exponent" />
</list>
</list>
<list>
<leaf symbol="LET" />
<leaf symbol="listOfFactors" />
<list>
<leaf symbol="rest" />
<leaf symbol="listOfFactors" />
</list>
</list>
<list>
<leaf symbol="IF" />
<leaf symbol="info" />
<list>
<leaf symbol="SEQ" />
<list>
<leaf symbol="LET" />
<list>
<leaf symbol=":" />
<leaf symbol="lof" />
<list>
<leaf symbol="List" />
<list>
<leaf symbol="OutputForm" />
</list>
</list>
</list>
<list>
<leaf symbol="construct" />
<list>
<leaf symbol="message" />
<leaf string="just now we try to split the polynomial:" />
</list>
<list>
<leaf symbol="::" />
<leaf symbol="p" />
<list>
<leaf symbol="OutputForm" />
</list>
</list>
</list>
</list>
<list>
<leaf symbol="exit" />
<leaf int="1" />
<list>
<leaf symbol="print" />
<list>
<leaf symbol="vconcat" />
<leaf symbol="lof" />
</list>
</list>
</list>
</list>
<leaf symbol="noBranch" />
</list>
<list>
<leaf symbol="LET" />
<list>
<leaf symbol=":" />
<leaf symbol="split" />
<list>
<leaf symbol="Factored" />
<leaf symbol="UP" />
</list>
</list>
<list>
<leaf symbol="pleskenSplit" />
<leaf symbol="p" />
<leaf symbol="eps0" />
<leaf symbol="info" />
</list>
</list>
<list>
<leaf symbol="LET" />
<list>
<leaf symbol=":" />
<leaf symbol="G15840052" />
<list>
<leaf symbol="Boolean" />
</list>
</list>
<list>
<leaf symbol="=" />
<list>
<leaf symbol="numberOfFactors" />
<leaf symbol="split" />
</list>
<list>
<leaf symbol="One" />
</list>
</list>
</list>
<list>
<leaf symbol="exit" />
<leaf int="1" />
<list>
<leaf symbol="IF" />
<leaf symbol="G15840052" />
<list>
<leaf symbol="SEQ" />
<list>
<leaf symbol="LET" />
<list>
<leaf symbol=":" />
<leaf symbol="lof" />
<list>
<leaf symbol="List" />
<list>
<leaf symbol="OutputForm" />
</list>
</list>
</list>
<list>
<leaf symbol="construct" />
<list>
<leaf symbol="message" />
<leaf string="factor: couldn't split factor" />
</list>
<list>
<leaf symbol="center" />
<list>
<leaf symbol="::" />
<leaf symbol="p" />
<list>
<leaf symbol="OutputForm" />
</list>
</list>
</list>
<list>
<leaf symbol="message" />
<leaf string="with required error bound" />
</list>
</list>
</list>
<list>
<leaf symbol="print" />
<list>
<leaf symbol="vconcat" />
<leaf symbol="lof" />
</list>
</list>
<list>
<leaf symbol="exit" />
<leaf int="1" />
<list>
<leaf symbol="LET" />
<leaf symbol="result" />
<list>
<leaf symbol="*" />
<leaf symbol="result" />
<list>
<leaf symbol="nilFactor" />
<leaf symbol="p" />
<leaf symbol="exponentOfp" />
</list>
</list>
</list>
</list>
</list>
<list>
<leaf symbol="REPEAT" />
<list>
<leaf symbol="IN" />
<leaf symbol="rec" />
<list>
<list>
<leaf symbol="Sel" />
<list>
<leaf symbol="Factored" />
<leaf symbol="UP" />
</list>
<leaf symbol="factors" />
</list>
<leaf symbol="split" />
</list>
</list>
<list>
<leaf symbol="SEQ" />
<list>
<leaf symbol="LET" />
<list>
<leaf symbol=":" />
<leaf symbol="newFactor" />
<leaf symbol="UP" />
</list>
<list>
<leaf symbol="rec" />
<leaf symbol="factor" />
</list>
</list>
<list>
<leaf symbol="LET" />
<leaf symbol="expOfFactor" />
<list>
<leaf symbol="*" />
<leaf symbol="exponentOfp" />
<list>
<leaf symbol="rec" />
<leaf symbol="exponent" />
</list>
</list>
</list>
<list>
<leaf symbol="LET" />
<list>
<leaf symbol=":" />
<leaf symbol="G15840053" />
<list>
<leaf symbol="Boolean" />
</list>
</list>
<list>
<leaf symbol="=" />
<list>
<leaf symbol="degree" />
<leaf symbol="newFactor" />
</list>
<list>
<leaf symbol="One" />
</list>
</list>
</list>
<list>
<leaf symbol="exit" />
<leaf int="1" />
<list>
<leaf symbol="IF" />
<leaf symbol="G15840053" />
<list>
<leaf symbol="LET" />
<leaf symbol="result" />
<list>
<leaf symbol="*" />
<leaf symbol="result" />
<list>
<leaf symbol="nilFactor" />
<leaf symbol="newFactor" />
<leaf symbol="expOfFactor" />
</list>
</list>
</list>
<list>
<leaf symbol="LET" />
<leaf symbol="listOfFactors" />
<list>
<leaf symbol="cons" />
<list>
<leaf symbol="construct" />
<leaf symbol="newFactor" />
<leaf symbol="expOfFactor" />
</list>
<leaf symbol="listOfFactors" />
</list>
</list>
</list>
</list>
</list>
</list>
</list>
</list>
</list>
</list>
<list>
<leaf symbol="exit" />
<leaf int="1" />
<leaf symbol="result" />
</list>
</list>
</list>
</list>
</list>
</list>
<list>
<leaf symbol="DEF" />
<list>
<leaf symbol="absC" />
<leaf symbol="c" />
</list>
<list>
<list />
<list />
</list>
<list>
<list />
<list />
</list>
<list>
<leaf symbol="nthRoot" />
<list>
<list>
<leaf symbol="Sel" />
<list>
<leaf symbol="Complex" />
<leaf symbol="R" />
</list>
<leaf symbol="norm" />
</list>
<leaf symbol="c" />
</list>
<leaf int="2" />
</list>
</list>
<list>
<leaf symbol="DEF" />
<list>
<leaf symbol="absR" />
<leaf symbol="r" />
</list>
<list>
<list />
<list />
</list>
<list>
<list />
<list />
</list>
<list>
<leaf symbol="IF" />
<list>
<leaf symbol="&lt;" />
<leaf symbol="r" />
<list>
<leaf symbol="Zero" />
</list>
</list>
<list>
<leaf symbol="-" />
<leaf symbol="r" />
</list>
<leaf symbol="r" />
</list>
</list>
<list>
<leaf symbol="DEF" />
<list>
<leaf symbol="min" />
<leaf symbol="fae1" />
<leaf symbol="fae2" />
</list>
<list>
<list />
<list />
<list />
</list>
<list>
<list />
<list />
<list />
</list>
<list>
<leaf symbol="SEQ" />
<list>
<leaf symbol="LET" />
<list>
<leaf symbol=":" />
<leaf symbol="G15840054" />
<list>
<leaf symbol="Boolean" />
</list>
</list>
<list>
<leaf symbol="&lt;" />
<list>
<leaf symbol="fae2" />
<leaf symbol="error" />
</list>
<list>
<leaf symbol="fae1" />
<leaf symbol="error" />
</list>
</list>
</list>
<list>
<leaf symbol="exit" />
<leaf int="1" />
<list>
<leaf symbol="IF" />
<leaf symbol="G15840054" />
<leaf symbol="fae2" />
<leaf symbol="fae1" />
</list>
</list>
</list>
</list>
<list>
<leaf symbol="DEF" />
<list>
<leaf symbol="calculateScale" />
<leaf symbol="p" />
</list>
<list>
<list />
<list />
</list>
<list>
<list />
<list />
</list>
<list>
<leaf symbol="SEQ" />
<list>
<leaf symbol="LET" />
<leaf symbol="d" />
<list>
<leaf symbol="degree" />
<leaf symbol="p" />
</list>
</list>
<list>
<leaf symbol="LET" />
<list>
<leaf symbol=":" />
<leaf symbol="maxi" />
<leaf symbol="R" />
</list>
<list>
<leaf symbol="Zero" />
</list>
</list>
<list>
<leaf symbol="REPEAT" />
<list>
<leaf symbol="IN" />
<leaf symbol="mon" />
<list>
<leaf symbol="rest" />
<list>
<leaf symbol="monomials" />
<leaf symbol="p" />
</list>
</list>
</list>
<list>
<leaf symbol="SEQ" />
<list>
<leaf symbol="LET" />
<leaf symbol="j" />
<list>
<leaf symbol="@" />
<list>
<leaf symbol="qcoerce" />
<list>
<leaf symbol="-" />
<leaf symbol="d" />
<list>
<leaf symbol="degree" />
<leaf symbol="mon" />
</list>
</list>
</list>
<list>
<leaf symbol="NonNegativeInteger" />
</list>
</list>
</list>
<list>
<leaf symbol="LET" />
<leaf symbol="cof" />
<list>
<leaf symbol="leadingCoefficient" />
<leaf symbol="mon" />
</list>
</list>
<list>
<leaf symbol="LET" />
<list>
<leaf symbol=":" />
<leaf symbol="rc" />
<leaf symbol="R" />
</list>
<list>
<leaf symbol="absR" />
<list>
<leaf symbol="real" />
<leaf symbol="cof" />
</list>
</list>
</list>
<list>
<leaf symbol="LET" />
<list>
<leaf symbol=":" />
<leaf symbol="ic" />
<leaf symbol="R" />
</list>
<list>
<leaf symbol="absR" />
<list>
<leaf symbol="imag" />
<leaf symbol="cof" />
</list>
</list>
</list>
<list>
<leaf symbol="LET" />
<list>
<leaf symbol=":" />
<leaf symbol="locmax" />
<leaf symbol="R" />
</list>
<list>
<leaf symbol="max" />
<leaf symbol="rc" />
<leaf symbol="ic" />
</list>
</list>
<list>
<leaf symbol="exit" />
<leaf int="1" />
<list>
<leaf symbol="LET" />
<leaf symbol="maxi" />
<list>
<leaf symbol="max" />
<list>
<leaf symbol="nthRoot" />
<list>
<leaf symbol="/" />
<leaf symbol="locmax" />
<list>
<leaf symbol="::" />
<list>
<list>
<leaf symbol="Sel" />
<list>
<leaf symbol="IntegerCombinatoricFunctions" />
<list>
<leaf symbol="Integer" />
</list>
</list>
<leaf symbol="binomial" />
</list>
<leaf symbol="d" />
<leaf symbol="j" />
</list>
<leaf symbol="R" />
</list>
</list>
<leaf symbol="j" />
</list>
<leaf symbol="maxi" />
</list>
</list>
</list>
</list>
</list>
<list>
<leaf symbol="LET" />
<list>
<leaf symbol=":" />
<leaf symbol="G15840055" />
<list>
<leaf symbol="Boolean" />
</list>
</list>
<list>
<leaf symbol="=" />
<leaf symbol="maxi" />
<list>
<leaf symbol="Sel" />
<leaf symbol="R" />
<list>
<leaf symbol="Zero" />
</list>
</list>
</list>
</list>
<list>
<leaf symbol="exit" />
<leaf int="1" />
<list>
<leaf symbol="IF" />
<leaf symbol="G15840055" />
<list>
<leaf symbol="error" />
<leaf string="Internal Error: scale cannot be 0" />
</list>
<list>
<leaf symbol="SEQ" />
<list>
<leaf symbol="LET" />
<list>
<leaf symbol=":" />
<leaf symbol="rho" />
<leaf symbol="R" />
</list>
<leaf symbol="one" />
</list>
<list>
<leaf symbol="exit" />
<leaf int="1" />
<list>
<leaf symbol="IF" />
<list>
<leaf symbol="&lt;" />
<leaf symbol="rho" />
<leaf symbol="maxi" />
</list>
<list>
<leaf symbol="SEQ" />
<list>
<leaf symbol="REPEAT" />
<list>
<leaf symbol="WHILE" />
<list>
<leaf symbol="&lt;" />
<leaf symbol="rho" />
<leaf symbol="maxi" />
</list>
</list>
<list>
<leaf symbol="LET" />
<leaf symbol="rho" />
<list>
<leaf symbol="*" />
<leaf symbol="ten" />
<leaf symbol="rho" />
</list>
</list>
</list>
<list>
<leaf symbol="exit" />
<leaf int="1" />
<list>
<leaf symbol="/" />
<leaf symbol="rho" />
<leaf symbol="ten" />
</list>
</list>
</list>
<list>
<leaf symbol="SEQ" />
<list>
<leaf symbol="REPEAT" />
<list>
<leaf symbol="WHILE" />
<list>
<leaf symbol="&lt;" />
<leaf symbol="maxi" />
<leaf symbol="rho" />
</list>
</list>
<list>
<leaf symbol="LET" />
<leaf symbol="rho" />
<list>
<leaf symbol="/" />
<leaf symbol="rho" />
<leaf symbol="ten" />
</list>
</list>
</list>
<list>
<leaf symbol="exit" />
<leaf int="1" />
<list>
<leaf symbol="IF" />
<list>
<leaf symbol="=" />
<leaf symbol="rho" />
<list>
<leaf symbol="Zero" />
</list>
</list>
<leaf symbol="one" />
<leaf symbol="rho" />
</list>
</list>
</list>
</list>
</list>
</list>
</list>
</list>
</list>
</list>
<list>
<leaf symbol="DEF" />
<list>
<leaf symbol="makeMonic" />
<leaf symbol="p" />
</list>
<list>
<list />
<list />
</list>
<list>
<list />
<list />
</list>
<list>
<leaf symbol="IF" />
<list>
<leaf symbol="=" />
<leaf symbol="p" />
<list>
<leaf symbol="Zero" />
</list>
</list>
<leaf symbol="p" />
<list>
<leaf symbol="+" />
<list>
<list>
<leaf symbol="Sel" />
<leaf symbol="UP" />
<leaf symbol="monomial" />
</list>
<list>
<leaf symbol="One" />
</list>
<list>
<leaf symbol="degree" />
<leaf symbol="p" />
</list>
</list>
<list>
<leaf symbol="/" />
<list>
<leaf symbol="reductum" />
<leaf symbol="p" />
</list>
<list>
<leaf symbol="leadingCoefficient" />
<leaf symbol="p" />
</list>
</list>
</list>
</list>
</list>
<list>
<leaf symbol="DEF" />
<list>
<leaf symbol="scale" />
<leaf symbol="p" />
<leaf symbol="c" />
</list>
<list>
<list />
<list />
<list />
</list>
<list>
<list />
<list />
<list />
</list>
<list>
<leaf symbol="SEQ" />
<list>
<leaf symbol="LET" />
<list>
<leaf symbol=":" />
<leaf symbol="eq" />
<list>
<leaf symbol="Equation" />
<leaf symbol="UP" />
</list>
</list>
<list>
<leaf symbol="equation" />
<list>
<leaf symbol="monomial" />
<list>
<leaf symbol="One" />
</list>
<list>
<leaf symbol="One" />
</list>
</list>
<list>
<leaf symbol="monomial" />
<leaf symbol="c" />
<list>
<leaf symbol="One" />
</list>
</list>
</list>
</list>
<list>
<leaf symbol="exit" />
<leaf int="1" />
<list>
<leaf symbol="eval" />
<leaf symbol="p" />
<leaf symbol="eq" />
</list>
</list>
</list>
</list>
<list>
<leaf symbol="DEF" />
<list>
<leaf symbol="shift" />
<leaf symbol="p" />
<leaf symbol="c" />
</list>
<list>
<list />
<list />
<list />
</list>
<list>
<list />
<list />
<list />
</list>
<list>
<leaf symbol="SEQ" />
<list>
<leaf symbol="LET" />
<list>
<leaf symbol=":" />
<leaf symbol="rhs" />
<leaf symbol="UP" />
</list>
<list>
<leaf symbol="+" />
<list>
<leaf symbol="monomial" />
<list>
<leaf symbol="One" />
</list>
<list>
<leaf symbol="One" />
</list>
</list>
<list>
<leaf symbol="monomial" />
<leaf symbol="c" />
<list>
<leaf symbol="Zero" />
</list>
</list>
</list>
</list>
<list>
<leaf symbol="LET" />
<list>
<leaf symbol=":" />
<leaf symbol="eq" />
<list>
<leaf symbol="Equation" />
<leaf symbol="UP" />
</list>
</list>
<list>
<leaf symbol="equation" />
<list>
<leaf symbol="monomial" />
<list>
<leaf symbol="One" />
</list>
<list>
<leaf symbol="One" />
</list>
</list>
<leaf symbol="rhs" />
</list>
</list>
<list>
<leaf symbol="exit" />
<leaf int="1" />
<list>
<leaf symbol="eval" />
<leaf symbol="p" />
<leaf symbol="eq" />
</list>
</list>
</list>
</list>
<list>
<leaf symbol="DEF" />
<list>
<leaf symbol="nthRoot" />
<leaf symbol="r" />
<leaf symbol="n" />
</list>
<list>
<list />
<list />
<list />
</list>
<list>
<list />
<list />
<list />
</list>
<list>
<leaf symbol="IF" />
<list>
<leaf symbol="has" />
<leaf symbol="R" />
<list>
<leaf symbol="RealNumberSystem" />
</list>
</list>
<list>
<leaf symbol="^" />
<leaf symbol="r" />
<list>
<leaf symbol="/" />
<list>
<leaf symbol="One" />
</list>
<leaf symbol="n" />
</list>
</list>
<list>
<leaf symbol="IF" />
<list>
<leaf symbol="has" />
<leaf symbol="R" />
<list>
<leaf symbol="QuotientFieldCategory" />
<list>
<leaf symbol="Integer" />
</list>
</list>
</list>
<list>
<leaf symbol="SEQ" />
<list>
<leaf symbol="LET" />
<list>
<leaf symbol=":" />
<leaf symbol="den" />
<list>
<leaf symbol="Integer" />
</list>
</list>
<list>
<list>
<leaf symbol="Sel" />
<list>
<leaf symbol="IntegerRoots" />
<list>
<leaf symbol="Integer" />
</list>
</list>
<leaf symbol="approxNthRoot" />
</list>
<list>
<leaf symbol="*" />
<leaf symbol="globalDigits" />
<list>
<leaf symbol="denom" />
<leaf symbol="r" />
</list>
</list>
<leaf symbol="n" />
</list>
</list>
<list>
<leaf symbol="LET" />
<list>
<leaf symbol=":" />
<leaf symbol="num" />
<list>
<leaf symbol="Integer" />
</list>
</list>
<list>
<list>
<leaf symbol="Sel" />
<list>
<leaf symbol="IntegerRoots" />
<list>
<leaf symbol="Integer" />
</list>
</list>
<leaf symbol="approxNthRoot" />
</list>
<list>
<leaf symbol="*" />
<leaf symbol="globalDigits" />
<list>
<leaf symbol="numer" />
<leaf symbol="r" />
</list>
</list>
<leaf symbol="n" />
</list>
</list>
<list>
<leaf symbol="exit" />
<leaf int="1" />
<list>
<leaf symbol="/" />
<leaf symbol="num" />
<leaf symbol="den" />
</list>
</list>
</list>
<list>
<leaf symbol="error" />
<leaf string="unimplemented" />
</list>
</list>
</list>
</list>
</list>
</list>
</func>
</file>
