<?xml version="1.0" encoding="UTF-8" standalone="no"?>
<file>
<func>
<list>
<leaf symbol="DEF" />
<list>
<leaf symbol="HashState" />
</list>
<list>
<list>
<leaf symbol="CATEGORY" />
<leaf symbol="domain" />
<list>
<leaf symbol="SIGNATURE" />
<leaf symbol="new" />
<list>
<leaf symbol="$" />
</list>
</list>
<list>
<leaf symbol="SIGNATURE" />
<leaf symbol="update!" />
<list>
<leaf symbol="$" />
<leaf symbol="$" />
<list>
<leaf symbol="SingleInteger" />
</list>
</list>
</list>
<list>
<leaf symbol="SIGNATURE" />
<leaf symbol="value" />
<list>
<list>
<leaf symbol="SingleInteger" />
</list>
<leaf symbol="$" />
</list>
</list>
</list>
</list>
<list>
<list />
</list>
<list>
<leaf symbol="CAPSULE" />
<list>
<leaf symbol="MDEF" />
<list>
<leaf symbol="rep" />
<leaf symbol="x" />
</list>
<list>
<list />
<list />
</list>
<list>
<list />
<list />
</list>
<list>
<leaf symbol="pretend" />
<list>
<leaf symbol="@" />
<leaf symbol="x" />
<leaf symbol="$" />
</list>
<leaf symbol="Rep" />
</list>
</list>
<list>
<leaf symbol="MDEF" />
<list>
<leaf symbol="per" />
<leaf symbol="x" />
</list>
<list>
<list />
<list />
</list>
<list>
<list />
<list />
</list>
<list>
<leaf symbol="pretend" />
<list>
<leaf symbol="@" />
<leaf symbol="x" />
<leaf symbol="Rep" />
</list>
<leaf symbol="$" />
</list>
</list>
<list>
<leaf symbol="MDEF" />
<list>
<leaf symbol="I" />
</list>
<list>
<list />
</list>
<list>
<list />
</list>
<list>
<leaf symbol="SingleInteger" />
</list>
</list>
<list>
<leaf symbol="MDEF" />
<list>
<leaf symbol="Rep" />
</list>
<list>
<list />
</list>
<list>
<list />
</list>
<list>
<leaf symbol="Integer" />
</list>
</list>
<list>
<leaf symbol="DEF" />
<list>
<leaf symbol="new" />
</list>
<list>
<leaf symbol="$" />
</list>
<list>
<list />
</list>
<list>
<leaf symbol="per" />
<list>
<leaf symbol="Sel" />
<leaf symbol="Lisp" />
<leaf symbol="HASHSTATEBASIS" />
</list>
</list>
</list>
<list>
<leaf symbol="DEF" />
<list>
<leaf symbol="value" />
<leaf symbol="hs" />
</list>
<list>
<leaf symbol="I" />
<leaf symbol="$" />
</list>
<list>
<list />
<list />
</list>
<list>
<leaf symbol="pretend" />
<list>
<list>
<leaf symbol="Sel" />
<leaf symbol="Lisp" />
<leaf symbol="HASHSTATEMAKEFIXNUM" />
</list>
<leaf symbol="hs" />
</list>
<leaf symbol="I" />
</list>
</list>
<list>
<leaf symbol="DEF" />
<list>
<leaf symbol="update!" />
<leaf symbol="hs" />
<leaf symbol="i" />
</list>
<list>
<leaf symbol="$" />
<leaf symbol="$" />
<leaf symbol="I" />
</list>
<list>
<list />
<list />
<list />
</list>
<list>
<leaf symbol="per" />
<list>
<list>
<leaf symbol="Sel" />
<leaf symbol="Lisp" />
<leaf symbol="HASHSTATEUPDATE" />
</list>
<leaf symbol="hs" />
<leaf symbol="i" />
</list>
</list>
</list>
<list>
<leaf symbol="DEF" />
<list>
<leaf symbol="modulo" />
<leaf symbol="hs" />
<leaf symbol="i" />
</list>
<list>
<leaf symbol="I" />
<leaf symbol="$" />
<leaf symbol="I" />
</list>
<list>
<list />
<list />
<list />
</list>
<list>
<leaf symbol="pretend" />
<list>
<list>
<leaf symbol="Sel" />
<leaf symbol="Lisp" />
<leaf symbol="HASHSTATEMOD" />
</list>
<leaf symbol="hs" />
<leaf symbol="i" />
</list>
<leaf symbol="I" />
</list>
</list>
</list>
</list>
</func>
</file>
